argchoose/ArgChooser.py
argchoose/__init__.py
argchoose-0.1.dist-info/LICENSE
argchoose-0.1.dist-info/METADATA
argchoose-0.1.dist-info/WHEEL
argchoose-0.1.dist-info/top_level.txt
argchoose-0.1.dist-info/RECORD
