Metadata-Version: 2.1
Name: argchoose
Version: 0.1
Summary: Choose which functions to execute by simply creating clear cmdline menu and cmdline args parser in one step
Home-page: https://github.com/Djkusik/ArgChooser
Author: Paweł Kusiński
Author-email: KusinskiP@protonmail.com
License: MIT
Download-URL: https://github.com/Djkusik/ArgChooser/archive/v0.1.tar.gz
Keywords: cmdline,function,parser,menu,commandline,execute,create,args,arguments,easy,fast
Platform: UNKNOWN
Classifier: Environment :: Console
Classifier: Intended Audience :: Developers
Classifier: License :: OSI Approved :: MIT License
Classifier: Operating System :: Microsoft :: Windows
Classifier: Operating System :: POSIX :: Linux
Classifier: Programming Language :: Python :: 3
Classifier: Programming Language :: Python :: 3.8
Requires-Dist: PyInquirer
Requires-Dist: argparse
